{
  "sample_idx": 146,
  "source_shap_json": "/home/ejhan/AML/SHAP/Final Local Shap/shap_tuples_non_prefix_146.json",
  "true_label": "GOOD CREDIT RISK",
  "prediction_label": "GOOD CREDIT RISK",
  "prediction_probability": 0.2529526572112226,
  "prediction_threshold": 0.56,
  "final_explanation": "Based on the AI model's prediction, this application indicates a low credit risk. The length of the loan term significantly decreases the overall risk, while the applicant's credit history involving critical accounts or other existing credits further lowers the risk. Conversely, the absence of a checking account slightly increases the risk. Together, these factors combine to support a favorable credit risk assessment.",
  "final_explanation_ko": "본 AI가 예측한 결과에 따르면,\n고객은 채무 불이행 위험이 낮은 수준으로 평가됩니다. 대출 기간이 길수록 위험이 감소하는 경향이 있으며, 신청자의 신용 이력 중 신용 문제 이력이나 기존 대출이 위험을 더욱 낮춥니다. 반면에 입출금 계좌가 없는 것은 위험을 약간 증가시킵니다. 이러한 요소들이 결합되어 신용 위험 평가가 긍정적으로 이루어집니다.\n전반적으로 신용 위험이 낮은 수준으로 평가되어 대출 승인 가능성이 높습니다.",
  "shap_features": [
    {
      "rank": 1,
      "feature": "duration",
      "definition": "Loan duration in months.",
      "shap_value": -0.14906728403420563,
      "abs_shap": 0.14906728403420563,
      "direction": "decrease_risk"
    },
    {
      "rank": 2,
      "feature": "credit_history_critical/other existing credit",
      "definition": "Credit history: critical account or other existing credits.",
      "shap_value": -0.080080625499018,
      "abs_shap": 0.080080625499018,
      "direction": "decrease_risk"
    },
    {
      "rank": 3,
      "feature": "checking_status_no checking",
      "definition": "Checking account status: no checking account.",
      "shap_value": 0.04757475527587396,
      "abs_shap": 0.04757475527587396,
      "direction": "increase_risk"
    }
  ]
}
