{
  "sample_idx": 31,
  "shap_json_path": "SHAP/100 Local Shap/shap_tuples_non_prefix_31.json",
  "queries": [
    {
      "feature_rank": 1,
      "feature": "duration",
      "feature_definition": "Loan duration in months.",
      "feature_direction": "decrease_risk",
      "question": "Empirical analysis of loan duration in months as a determinant of reduced credit risk and default probability."
    },
    {
      "feature_rank": 2,
      "feature": "purpose_radio/tv",
      "feature_definition": "Loan purpose: purchase of radio or TV.",
      "feature_direction": "decrease_risk",
      "question": "Statistical impact of loan purpose for purchase of radio or TV on the mitigation of credit risk exposure."
    },
    {
      "feature_rank": 3,
      "feature": "checking_status_no checking",
      "feature_definition": "Checking account status: no checking account.",
      "feature_direction": "increase_risk",
      "question": "Determinants of credit default associated with the absence of a checking account and increased risk exposure."
    }
  ]
}