{
  "sample_idx": 536,
  "true_label": "GOOD CREDIT RISK",
  "prediction": {
    "label": "GOOD CREDIT RISK",
    "probability": 0.42174637573847534,
    "threshold": 0.56
  },
  "tuples": [
    {
      "feature": "duration",
      "definition": "Loan duration in months.",
      "shap_value": -0.1315311773041408,
      "abs_shap": 0.1315311773041408,
      "direction": "decrease_risk"
    },
    {
      "feature": "checking_status_<0",
      "definition": "Checking account status: balance below 0 DM.",
      "shap_value": 0.057130771172534234,
      "abs_shap": 0.057130771172534234,
      "direction": "increase_risk"
    },
    {
      "feature": "checking_status_no checking",
      "definition": "Checking account status: no checking account.",
      "shap_value": 0.045990928636866484,
      "abs_shap": 0.045990928636866484,
      "direction": "increase_risk"
    }
  ]
}