{
  "sample_idx": 723,
  "true_label": "GOOD CREDIT RISK",
  "prediction": {
    "label": "GOOD CREDIT RISK",
    "probability": 0.374554346714582,
    "threshold": 0.56
  },
  "tuples": [
    {
      "feature": "duration",
      "definition": "Loan duration in months.",
      "shap_value": -0.07670746459541694,
      "abs_shap": 0.07670746459541694,
      "direction": "decrease_risk"
    },
    {
      "feature": "checking_status_no checking",
      "definition": "Checking account status: no checking account.",
      "shap_value": 0.051768946466636434,
      "abs_shap": 0.051768946466636434,
      "direction": "increase_risk"
    },
    {
      "feature": "purpose_radio/tv",
      "definition": "Loan purpose: purchase of radio or TV.",
      "shap_value": -0.034429930433784256,
      "abs_shap": 0.034429930433784256,
      "direction": "decrease_risk"
    }
  ]
}