{
  "sample_idx": 70,
  "prediction_label": "GOOD CREDIT RISK",
  "prediction_probability": 0.41621843491178695,
  "final_explanation": "Based on the AI model's prediction,\nThe fact that the loan duration is shorter, because shorter loan terms effectively mitigate credit risk drivers, is known in the literature as a signal that decreases credit risk, and the model also identifies it as a factor that decreases risk.[1]\nThe fact that the requested credit amount is higher, because larger loan exposures inherently amplify repayment uncertainty, is known in the literature as a signal that increases credit risk, and the model also identifies it as a factor that increases risk.[2]\nThe fact that there is no known savings account, because account status is a critical determinant in credit risk modeling, is known in the literature as a signal that affects credit risk, and the model also identifies it as a factor that decreases risk.[3]\nOverall, this applicant is likely to have a low risk of default.",
  "evidence": [
    {
      "ref": 1,
      "feature": "duration",
      "evidence_sentences": [
        {
          "sentence": "Empirical work has exam- ined how demographic characteristics, such as age and marital status, and loan terms, such as loan size and interest rate, affect the borrower’s ability to repay on time (Özdemir, 2008).",
          "source": "regression-based credit risk modeling.pdf",
          "page": 8,
          "score": 0.17614662647247314
        },
        {
          "sentence": "OLS also lays a solid foundation for Tikhonov regularization and logistic regression analysis.",
          "source": "regression-based credit risk modeling.pdf",
          "page": 24,
          "score": 0.18175935745239258
        },
        {
          "sentence": "ﬁnancial organizations, loan institutes, and other decision-makers to predict the loan defaulter earlier.",
          "source": "An_Investigation_of_Credit_Card_Default_Prediction_in_the_Imbalanced_Datasets.pdf",
          "page": 2,
          "score": 0.19682347774505615
        },
        {
          "sentence": "These ratios reveal their accessibility and regularization capabilities of predic- tion.",
          "source": "An_Investigation_of_Credit_Card_Default_Prediction_in_the_Imbalanced_Datasets.pdf",
          "page": 3,
          "score": 0.19986200332641602
        },
        {
          "sentence": "Arslan 252 Page 8 of 23 loan default.",
          "source": "Comparison of the impact of dimensionality reduction and data splitting on classification performance in credit risk assessment .pdf",
          "page": 9,
          "score": 0.20412307977676392
        },
        {
          "sentence": "(i.e. the default probability) increases for longer maturity time, whereas from roughly four years (45 months) onwards the risk stays constantly high.",
          "source": "How much do we see? On the explainability of partial dependence plots for credit risk scoring.pdf",
          "page": 6,
          "score": 0.20517414808273315
        }
      ]
    },
    {
      "ref": 2,
      "feature": "credit_amount",
      "evidence_sentences": [
        {
          "sentence": "These effects correspond to the- oretical expectations, indicating that longer durations and higher credit amounts increase the likelihood of credit risk.",
          "source": "regression-based credit risk modeling.pdf",
          "page": 24,
          "score": 0.18307161331176758
        },
        {
          "sentence": "As a result, if a potential client already has a credit card with a high credit limit line, this person is improbable to fail to pay the full amount owed in the future.",
          "source": "An_Investigation_of_Credit_Card_Default_Prediction_in_the_Imbalanced_Datasets.pdf",
          "page": 25,
          "score": 0.18510347604751587
        },
        {
          "sentence": "If credit risk is underestimated and losses are realised, these costs are passed on to the customers through higher interest",
          "source": "regression-based credit risk modeling.pdf",
          "page": 7,
          "score": 0.1946658492088318
        },
        {
          "sentence": "AI/ML significantly benefits P2P lenders, FinTech companies, and traditional banks by enhancing the precision of credit scoring and default probability estimation for applicants (Doumpos et al., 2023;",
          "source": "Explainable Automated Machine Learning for Credit Decisions.pdf",
          "page": 3,
          "score": 0.19491863250732422
        }
      ]
    },
    {
      "ref": 3,
      "feature": "savings_status_no known savings",
      "evidence_sentences": [
        {
          "sentence": "The stan- dard model depends on the ﬁnancial ratios, income account, and data on the balance sheet [6], [7].",
          "source": "An_Investigation_of_Credit_Card_Default_Prediction_in_the_Imbalanced_Datasets.pdf",
          "page": 3,
          "score": 0.1865859031677246
        },
        {
          "sentence": "default client from non-defaulted [8] because these parame- ters may enhance the performance of models.",
          "source": "An_Investigation_of_Credit_Card_Default_Prediction_in_the_Imbalanced_Datasets.pdf",
          "page": 3,
          "score": 0.19822275638580322
        },
        {
          "sentence": "OLS also lays a solid foundation for Tikhonov regularization and logistic regression analysis.",
          "source": "regression-based credit risk modeling.pdf",
          "page": 24,
          "score": 0.20026373863220215
        },
        {
          "sentence": "Both accuracy and explainability are essential in aligning credit risk decisions with the dynamic demands o f the digital economy.",
          "source": "Explainable Automated Machine Learning for Credit Decisions.pdf",
          "page": 7,
          "score": 0.20300757884979248
        },
        {
          "sentence": "In practice, the results highlight the importance of lenders carefully inspecting the applicant’s account status, credit history, and the loan’s terms.",
          "source": "regression-based credit risk modeling.pdf",
          "page": 30,
          "score": 0.20496809482574463
        },
        {
          "sentence": "and low-risk groups with the information like gender, age and savings account.",
          "source": "The Application of Tree-based model to Unbalanced German Credit Data Analysis.pdf",
          "page": 3,
          "score": 0.20633196830749512
        },
        {
          "sentence": "SHAP analysis conﬁrmed the primacy of features like 'Duration' and 'Credit Amount' while also uncovering subtle distinctions in feature interaction between the models.",
          "source": "Comparison Between XGBoost and Random Forest in Credit Risk Assessment Using the German Credit Dataset.pdf",
          "page": 3,
          "score": 0.20932650566101074
        },
        {
          "sentence": "(2024).",
          "source": "Explainable Automated Machine Learning for Credit Decisions.pdf",
          "page": 17,
          "score": 0.21763849258422852
        },
        {
          "sentence": "IV.",
          "source": "Credit Scoring Using Data Mining Techniques.pdf",
          "page": 5,
          "score": 0.2186909317970276
        }
      ]
    }
  ],
  "final_explanation_ko": "본 AI가 예측한 결과에 따르면,\\n대출 기간이 짧을수록 신용 위험 요인들이 완화되므로 신용 위험이 감소하는 신호로 인식되며, 본 모델 역시 이를 위험 감소 요인으로 판단합니다 [1].\n대출 금액이 클수록 대출 노출이 커져 상환 불확실성이 증가하므로 신용 위험이 상승하는 신호로 인식되며, 본 모델 또한 이를 위험 증가 요인으로 식별합니다 [2].\n저축 계좌가 없는 경우, 계좌 상태가 신용 위험 본 모델링에서 중요한 결정 요인이므로 신용 위험에 영향을 미치는 요인으로 간주되며, 본 모델 역시 이를 위험 감소 요인으로 판단합니다 [3].\n전반적으로 이 고객은 채무 불이행 위험이 낮은 수준으로 평가됩니다."
}
