{
  "sample_idx": 82,
  "prediction_label": "BAD CREDIT RISK",
  "prediction_probability": 0.5848125733996071,
  "final_explanation": "Based on the AI model's prediction,\nThe fact that the checking account balance is negative, because it reflects active financial distress, is known in the literature as a signal that increases credit risk, and the model also identifies it as a factor that increases risk.[1]\nThe fact that the loan duration is extended, because extended repayment horizons amplify lender exposure to borrower financial deterioration, is known in the literature as a signal that increases credit risk, and the model also identifies it as a factor that increases risk.[2]\nThe fact that there is no checking account, due to the complete absence of a checking account correlating with a more favorable credit profile, is known in the literature as a signal that decreases credit risk, but the model instead identifies it as a factor that increases risk.[3]\nOverall, this applicant is likely to have a high risk of default.",
  "evidence": [
    {
      "ref": 1,
      "feature": "checking_status_<0",
      "evidence_sentences": [
        {
          "sentence": "default client from non-defaulted [8] because these parame- ters may enhance the performance of models.",
          "source": "An_Investigation_of_Credit_Card_Default_Prediction_in_the_Imbalanced_Datasets.pdf",
          "page": 3,
          "score": 0.22018706798553467
        },
        {
          "sentence": "Applicants with a checking account balance below 0 DM (Deutsche Mark) exhibit a substantially higher estimated risk relative to the reference group, while the category of no checking account is associated with a lower estimated risk in this",
          "source": "regression-based credit risk modeling.pdf",
          "page": 30,
          "score": 0.220838725566864
        },
        {
          "sentence": "The no checking account category has lower estimated log-odds compared to the baseline, with an odds ratio ofe −0.898 ≈0.41.",
          "source": "regression-based credit risk modeling.pdf",
          "page": 27,
          "score": 0.22223305702209473
        },
        {
          "sentence": "The stan- dard model depends on the ﬁnancial ratios, income account, and data on the balance sheet [6], [7].",
          "source": "An_Investigation_of_Credit_Card_Default_Prediction_in_the_Imbalanced_Datasets.pdf",
          "page": 3,
          "score": 0.227289080619812
        },
        {
          "sentence": "However, there are two unique features in credit evaluation analysis.",
          "source": "The Application of Tree-based model to Unbalanced German Credit Data Analysis.pdf",
          "page": 3,
          "score": 0.22913110256195068
        },
        {
          "sentence": "Both accuracy and explainability are essential in aligning credit risk decisions with the dynamic demands o f the digital economy.",
          "source": "Explainable Automated Machine Learning for Credit Decisions.pdf",
          "page": 7,
          "score": 0.230194091796875
        },
        {
          "sentence": "(2024).",
          "source": "Explainable Automated Machine Learning for Credit Decisions.pdf",
          "page": 17,
          "score": 0.2314741611480713
        },
        {
          "sentence": "The sign of the respective coefficients remains negative although",
          "source": "Interest and credit risk management in German banks.pdf",
          "page": 17,
          "score": 0.2350364327430725
        }
      ]
    },
    {
      "ref": 2,
      "feature": "duration",
      "evidence_sentences": [
        {
          "sentence": "These effects correspond to the- oretical expectations, indicating that longer durations and higher credit amounts increase the likelihood of credit risk.",
          "source": "regression-based credit risk modeling.pdf",
          "page": 24,
          "score": 0.17007684707641602
        },
        {
          "sentence": "Empirical work has exam- ined how demographic characteristics, such as age and marital status, and loan terms, such as loan size and interest rate, affect the borrower’s ability to repay on time (Özdemir, 2008).",
          "source": "regression-based credit risk modeling.pdf",
          "page": 8,
          "score": 0.17898112535476685
        },
        {
          "sentence": "These ratios reveal their accessibility and regularization capabilities of predic- tion.",
          "source": "An_Investigation_of_Credit_Card_Default_Prediction_in_the_Imbalanced_Datasets.pdf",
          "page": 3,
          "score": 0.18682128190994263
        },
        {
          "sentence": "• Risk Assessment Accuracy: In credit risk modeling, understanding the factors that influence a model's decision is crucial for accuracy and reliability.",
          "source": "Explainable Automated Machine Learning for Credit Decisions.pdf",
          "page": 13,
          "score": 0.1881689429283142
        },
        {
          "sentence": "ﬁnancial organizations, loan institutes, and other decision-makers to predict the loan defaulter earlier.",
          "source": "An_Investigation_of_Credit_Card_Default_Prediction_in_the_Imbalanced_Datasets.pdf",
          "page": 2,
          "score": 0.1939685344696045
        }
      ]
    },
    {
      "ref": 3,
      "feature": "checking_status_no checking",
      "evidence_sentences": [
        {
          "sentence": "while the category of no checking account is associated with a lower estimated risk in this dataset.",
          "source": "regression-based credit risk modeling.pdf",
          "page": 30,
          "score": 0.23834526538848877
        },
        {
          "sentence": "default client from non-defaulted [8] because these parame- ters may enhance the performance of models.",
          "source": "An_Investigation_of_Credit_Card_Default_Prediction_in_the_Imbalanced_Datasets.pdf",
          "page": 3,
          "score": 0.24367254972457886
        },
        {
          "sentence": "Applicants with a checking account balance below 0 DM (Deutsche Mark) exhibit a substantially higher estimated risk relative to the reference group, while the category of no checking account is associated with a lower estimated risk in this",
          "source": "regression-based credit risk modeling.pdf",
          "page": 30,
          "score": 0.2523941993713379
        },
        {
          "sentence": "This low-productivity, signiﬁcant expense conjectures cannot meet consumer ﬁnance enterprise’s credit",
          "source": "An_Investigation_of_Credit_Card_Default_Prediction_in_the_Imbalanced_Datasets.pdf",
          "page": 24,
          "score": 0.2556048631668091
        }
      ]
    }
  ]
}
