{
  "sample_idx": 109,
  "prediction_label": "BAD CREDIT RISK",
  "prediction_probability": 0.5957228738690054,
  "final_explanation": "Based on the AI model's prediction,\nThe fact that the checking account balance is negative, because of liquidity constraints signaling financial distress, is known in the literature as a signal that increases credit risk, and the model also identifies it as a factor that increases risk.[1]\nThe fact that the loan duration is extended, because of longer repayment periods amplifying uncertainty, is known in the literature as a signal that increases credit risk, but the model instead identifies it as a factor that decreases risk.[2]\nThe fact that there is no checking account, because of lack of direct liquidity tracking, is known in the literature as a signal that increases credit risk, and the model also identifies it as a factor that increases risk.[3]\nOverall, this applicant is likely to have a high risk of default.",
  "evidence": [
    {
      "ref": 1,
      "feature": "checking_status_<0",
      "evidence_sentences": [
        {
          "sentence": "Applicants with a checking account balance below 0 DM (Deutsche Mark) exhibit a substantially higher estimated risk relative to the reference group, while the category of no checking account is associated with a lower estimated risk in this",
          "source": "regression-based credit risk modeling.pdf",
          "page": 30,
          "score": 0.2172759771347046
        },
        {
          "sentence": "Applicants with a checking account balance below 0 DM (Deutsche Mark) exhibit a substantially higher estimated risk relative to the reference group, while the category of no checking account is associated with a lower estimated risk in this",
          "source": "regression-based credit risk modeling.pdf",
          "page": 30,
          "score": 0.21727770566940308
        },
        {
          "sentence": "However, there are two unique features in credit evaluation analysis.",
          "source": "The Application of Tree-based model to Unbalanced German Credit Data Analysis.pdf",
          "page": 3,
          "score": 0.2210075855255127
        },
        {
          "sentence": "However, there are two unique features in credit evaluation analysis.",
          "source": "The Application of Tree-based model to Unbalanced German Credit Data Analysis.pdf",
          "page": 3,
          "score": 0.2211371660232544
        },
        {
          "sentence": "D.",
          "source": "An_Investigation_of_Credit_Card_Default_Prediction_in_the_Imbalanced_Datasets.pdf",
          "page": 26,
          "score": 0.2227877974510193
        },
        {
          "sentence": "D.",
          "source": "An_Investigation_of_Credit_Card_Default_Prediction_in_the_Imbalanced_Datasets.pdf",
          "page": 26,
          "score": 0.22295188903808594
        }
      ]
    },
    {
      "ref": 2,
      "feature": "duration",
      "evidence_sentences": [
        {
          "sentence": "exposure at default secured by residential mortgages.",
          "source": "Interest and credit risk management in German banks.pdf",
          "page": 13,
          "score": 0.19852352142333984
        },
        {
          "sentence": "exposure at default secured by residential mortgages.",
          "source": "Interest and credit risk management in German banks.pdf",
          "page": 13,
          "score": 0.1986033320426941
        },
        {
          "sentence": "Both accuracy and explainability are essential in aligning credit risk decisions with the dynamic demands o f the digital economy.",
          "source": "Explainable Automated Machine Learning for Credit Decisions.pdf",
          "page": 7,
          "score": 0.19910377264022827
        },
        {
          "sentence": "Both accuracy and explainability are essential in aligning credit risk decisions with the dynamic demands o f the digital economy.",
          "source": "Explainable Automated Machine Learning for Credit Decisions.pdf",
          "page": 7,
          "score": 0.19911229610443115
        },
        {
          "sentence": "These effects correspond to the- oretical expectations, indicating that longer durations and higher credit amounts increase the likelihood of credit risk.",
          "source": "regression-based credit risk modeling.pdf",
          "page": 24,
          "score": 0.20216339826583862
        },
        {
          "sentence": "These effects correspond to the- oretical expectations, indicating that longer durations and higher credit amounts increase the likelihood of credit risk.",
          "source": "regression-based credit risk modeling.pdf",
          "page": 24,
          "score": 0.2023898959159851
        },
        {
          "sentence": "ﬁnancial organizations, loan institutes, and other decision-makers to predict the loan defaulter earlier.",
          "source": "An_Investigation_of_Credit_Card_Default_Prediction_in_the_Imbalanced_Datasets.pdf",
          "page": 2,
          "score": 0.20251226425170898
        },
        {
          "sentence": "ﬁnancial organizations, loan institutes, and other decision-makers to predict the loan defaulter earlier.",
          "source": "An_Investigation_of_Credit_Card_Default_Prediction_in_the_Imbalanced_Datasets.pdf",
          "page": 2,
          "score": 0.20256799459457397
        }
      ]
    },
    {
      "ref": 3,
      "feature": "checking_status_no checking",
      "evidence_sentences": [
        {
          "sentence": "1 1 Introduction Credit risk assessment remains a central challenge in modern finance, as lenders must evalu- ate the likelihood that borrowers will meet their obligations.",
          "source": "regression-based credit risk modeling.pdf",
          "page": 7,
          "score": 0.20741325616836548
        },
        {
          "sentence": "1 1 Introduction Credit risk assessment remains a central challenge in modern finance, as lenders must evalu- ate the likelihood that borrowers will meet their obligations.",
          "source": "regression-based credit risk modeling.pdf",
          "page": 7,
          "score": 0.20748740434646606
        },
        {
          "sentence": "For more information, see https://creativecommons.org/licenses/by/4.0/ 201173",
          "source": "An_Investigation_of_Credit_Card_Default_Prediction_in_the_Imbalanced_Datasets.pdf",
          "page": 2,
          "score": 0.21848994493484497
        },
        {
          "sentence": "For more information, see https://creativecommons.org/licenses/by/4.0/ 201173",
          "source": "An_Investigation_of_Credit_Card_Default_Prediction_in_the_Imbalanced_Datasets.pdf",
          "page": 2,
          "score": 0.21867424249649048
        }
      ]
    }
  ]
}
